MANIFEST.in
README.rst
setup.py
fabez/__init__.py
fabez/api.py
fabez/app.py
fabez/cloud.py
fabez/cmd.py
fabez/dev.py
fabez/docs.py
fabez/env.py
fabez/etc.py
fabez/git.py
fabez/io.py
fabez/lib.py
fabez/main.py
fabez/perm.py
fabez/pythonic.py
fabez/server.py
fabez/user.py
fabez/utils.py
fabez/web.py
fabez.egg-info/PKG-INFO
fabez.egg-info/SOURCES.txt
fabez.egg-info/dependency_links.txt
fabez.egg-info/entry_points.txt
fabez.egg-info/requires.txt
fabez.egg-info/top_level.txt
fabez/tpl/90-nproc.conf
fabez/tpl/cloud.yaml
fabez/tpl/fabfile.py
fabez/tpl/mconfigsvr.start
fabez/tpl/mongodb.repo
fabez/tpl/mongos.start
fabez/tpl/monit-graphite.conf
fabez/tpl/monit-statsd.conf
fabez/tpl/nginx.conf
fabez/tpl/nginx.start
fabez/tpl/nginx.sysconfig
fabez/tpl/php-fpm.conf
fabez/tpl/postfix.cf
fabez/tpl/supervisord.conf
fabez/tpl/supervisord.start
fabez/tpl/yaf.conf
fabez/tpl/web/__init__.py
fabez/tpl/web/app.py
fabez/tpl/web/config.py
fabez/tpl/web/handlers.py
fabez/tpl/web/settings.py
fabez/tpl/web/wsgi.py