Metadata-Version: 1.1
Name: fabez
Version: 0.8.41
Summary: A deploy tool for CentOS, based on fabric.
Home-page: https://github.com/baixing/cabric
Author: Breeze.Kay
Author-email: wangwenpei@nextoa.com
License: http://opensource.org/licenses/MIT
Download-URL: https://github.com/baixing/cabric/tarball/master
Keywords: fabric,fabez,cabric
Platform: UNKNOWN
